{
  "0": {
    "MISSION": "",
    "SEQUENCE_ID": "",
    "SCENARIO_STATUS": "800b0029fffffffe000b002a",
    "PLAYER": "",
    "MODEL_NAME": "",
    "STAGEID": "",
    "DAYNIGHT": "",
    "WEATHER": "",
    "DRIVE_MISSION": "",
    "GAME_MODE": "",
    "KAIWABGM_PLAYING": "",
    "DRIVE_CAMERA_IN_ROOM": "",
    "SELECT_COUNTER": "",
    "BATTLE_TYPE": "CROWDED"
  },
  "1": {
    "MISSION": "",
    "SEQUENCE_ID": "",
    "SCENARIO_STATUS": "800d001cfffffffe000d001e",
    "PLAYER": "",
    "MODEL_NAME": "",
    "STAGEID": "",
    "DAYNIGHT": "",
    "WEATHER": "",
    "DRIVE_MISSION": "",
    "GAME_MODE": "",
    "KAIWABGM_PLAYING": "",
    "DRIVE_CAMERA_IN_ROOM": "",
    "SELECT_COUNTER": "",
    "BATTLE_TYPE": "CROWDED"
  },
  "2": {
    "MISSION": "",
    "SEQUENCE_ID": "",
    "SCENARIO_STATUS": "800d001efffffffe000d0020",
    "PLAYER": "",
    "MODEL_NAME": "",
    "STAGEID": "",
    "DAYNIGHT": "",
    "WEATHER": "",
    "DRIVE_MISSION": "",
    "GAME_MODE": "",
    "KAIWABGM_PLAYING": "",
    "DRIVE_CAMERA_IN_ROOM": "",
    "SELECT_COUNTER": "",
    "BATTLE_TYPE": "CROWDED"
  },
  "3": {
    "MISSION": "",
    "SEQUENCE_ID": "",
    "SCENARIO_STATUS": "80130069fffffffe0013006a",
    "PLAYER": "",
    "MODEL_NAME": "",
    "STAGEID": "",
    "DAYNIGHT": "",
    "WEATHER": "",
    "DRIVE_MISSION": "",
    "GAME_MODE": "",
    "KAIWABGM_PLAYING": "",
    "DRIVE_CAMERA_IN_ROOM": "",
    "SELECT_COUNTER": "",
    "BATTLE_TYPE": "CROWDED"
  },
  "4": {
    "MISSION": "",
    "SEQUENCE_ID": "",
    "SCENARIO_STATUS": "80170015fffffffe00170016",
    "PLAYER": "",
    "MODEL_NAME": "",
    "STAGEID": "",
    "DAYNIGHT": "",
    "WEATHER": "",
    "DRIVE_MISSION": "",
    "GAME_MODE": "",
    "KAIWABGM_PLAYING": "",
    "DRIVE_CAMERA_IN_ROOM": "",
    "SELECT_COUNTER": "",
    "BATTLE_TYPE": "CROWDED"
  },
  "5": {
    "MISSION": "",
    "SEQUENCE_ID": "",
    "SCENARIO_STATUS": "801c000afffffffe001c000b",
    "PLAYER": "",
    "MODEL_NAME": "",
    "STAGEID": "",
    "DAYNIGHT": "",
    "WEATHER": "",
    "DRIVE_MISSION": "",
    "GAME_MODE": "",
    "KAIWABGM_PLAYING": "",
    "DRIVE_CAMERA_IN_ROOM": "",
    "SELECT_COUNTER": "",
    "BATTLE_TYPE": "CROWDED"
  },
  "6": {
    "MISSION": "",
    "SEQUENCE_ID": "",
    "SCENARIO_STATUS": "801c001afffffffe001c001b",
    "PLAYER": "",
    "MODEL_NAME": "",
    "STAGEID": "",
    "DAYNIGHT": "",
    "WEATHER": "",
    "DRIVE_MISSION": "",
    "GAME_MODE": "",
    "KAIWABGM_PLAYING": "",
    "DRIVE_CAMERA_IN_ROOM": "",
    "SELECT_COUNTER": "",
    "BATTLE_TYPE": "CROWDED"
  },
  "7": {
    "MISSION": "",
    "SEQUENCE_ID": "",
    "SCENARIO_STATUS": "801c001efffffffe001c001f",
    "PLAYER": "",
    "MODEL_NAME": "",
    "STAGEID": "",
    "DAYNIGHT": "",
    "WEATHER": "",
    "DRIVE_MISSION": "",
    "GAME_MODE": "",
    "KAIWABGM_PLAYING": "",
    "DRIVE_CAMERA_IN_ROOM": "",
    "SELECT_COUNTER": "",
    "BATTLE_TYPE": "CROWDED"
  },
  "8": {
    "MISSION": "",
    "SEQUENCE_ID": "",
    "SCENARIO_STATUS": "80160019fffffffe0016001a",
    "PLAYER": "",
    "MODEL_NAME": "",
    "STAGEID": "",
    "DAYNIGHT": "",
    "WEATHER": "",
    "DRIVE_MISSION": "",
    "GAME_MODE": "",
    "KAIWABGM_PLAYING": "",
    "DRIVE_CAMERA_IN_ROOM": "",
    "SELECT_COUNTER": "",
    "BATTLE_TYPE": "4_3_LONG_FORMER"
  },
  "9": {
    "MISSION": "",
    "SEQUENCE_ID": "",
    "SCENARIO_STATUS": "8016001afffffffe0016001b",
    "PLAYER": "",
    "MODEL_NAME": "",
    "STAGEID": "",
    "DAYNIGHT": "",
    "WEATHER": "",
    "DRIVE_MISSION": "",
    "GAME_MODE": "",
    "KAIWABGM_PLAYING": "",
    "DRIVE_CAMERA_IN_ROOM": "",
    "SELECT_COUNTER": "",
    "BATTLE_TYPE": "4_3_LONG_CHASE"
  },
  "10": {
    "MISSION": "",
    "SEQUENCE_ID": "",
    "SCENARIO_STATUS": "81840034",
    "PLAYER": "",
    "MODEL_NAME": "",
    "STAGEID": "",
    "DAYNIGHT": "",
    "WEATHER": "",
    "DRIVE_MISSION": "",
    "GAME_MODE": "",
    "KAIWABGM_PLAYING": "",
    "DRIVE_CAMERA_IN_ROOM": "",
    "SELECT_COUNTER": "",
    "BATTLE_TYPE": "ULTIMATE_CHASE_02"
  },
  "11": {
    "MISSION": "",
    "SEQUENCE_ID": "",
    "SCENARIO_STATUS": "81840036",
    "PLAYER": "",
    "MODEL_NAME": "",
    "STAGEID": "",
    "DAYNIGHT": "",
    "WEATHER": "",
    "DRIVE_MISSION": "",
    "GAME_MODE": "",
    "KAIWABGM_PLAYING": "",
    "DRIVE_CAMERA_IN_ROOM": "",
    "SELECT_COUNTER": "",
    "BATTLE_TYPE": "ULTIMATE_CHASE_03"
  },
  "12": {
    "MISSION": "",
    "SEQUENCE_ID": "",
    "SCENARIO_STATUS": "817e0000",
    "PLAYER": "",
    "MODEL_NAME": "",
    "STAGEID": "",
    "DAYNIGHT": "",
    "WEATHER": "",
    "DRIVE_MISSION": "",
    "GAME_MODE": "",
    "KAIWABGM_PLAYING": "",
    "DRIVE_CAMERA_IN_ROOM": "",
    "SELECT_COUNTER": "",
    "BATTLE_TYPE": "TUTORIAL"
  },
  "13": {
    "MISSION": "",
    "SEQUENCE_ID": "",
    "SCENARIO_STATUS": "8016001bfffffffe0016001c",
    "PLAYER": "",
    "MODEL_NAME": "",
    "STAGEID": "",
    "DAYNIGHT": "",
    "WEATHER": "",
    "DRIVE_MISSION": "",
    "GAME_MODE": "",
    "KAIWABGM_PLAYING": "",
    "DRIVE_CAMERA_IN_ROOM": "",
    "SELECT_COUNTER": "",
    "BATTLE_TYPE": "4_3_LONG_LATTER"
  },
  "14": {
    "MISSION": "",
    "SEQUENCE_ID": "",
    "SCENARIO_STATUS": "803c0003fffffffe003c0004",
    "PLAYER": "",
    "MODEL_NAME": "",
    "STAGEID": "",
    "DAYNIGHT": "",
    "WEATHER": "",
    "DRIVE_MISSION": "",
    "GAME_MODE": "",
    "KAIWABGM_PLAYING": "",
    "DRIVE_CAMERA_IN_ROOM": "",
    "SELECT_COUNTER": "",
    "BATTLE_TYPE": "SUB_B10_SYOKAKI"
  },
  "types": {
    "MISSION": "string",
    "SEQUENCE_ID": "string",
    "SCENARIO_STATUS": "special_scenariostatus",
    "PLAYER": "string",
    "MODEL_NAME": "string",
    "STAGEID": "stageid",
    "DAYNIGHT": "string",
    "WEATHER": "string",
    "DRIVE_MISSION": "string",
    "GAME_MODE": "string",
    "KAIWABGM_PLAYING": "string",
    "DRIVE_CAMERA_IN_ROOM": "string",
    "SELECT_COUNTER": "string",
    "BATTLE_TYPE": "string"
  }
}